{"cameraMode":{"drawMode":0,"name":"Shaded","section":"Shading Mode"},"sceneLighting":true,"audioPlay":false,"sceneViewState":{"showFog":true,"showMaterialUpdate":false,"showSkybox":true,"showFlares":true,"showImageEffects":true,"showParticleSystems":true},"in2DMode":false,"pivot":{"x":18.00647735595703,"y":5.221017837524414,"z":-15.940094947814942},"rotation":{"x":-0.3568068742752075,"y":0.5769952535629273,"z":-0.30878767371177676,"w":-0.6666719913482666},"size":6.899963855743408,"orthographic":false}